{".class": "MypyFile", "_fullname": "pyexceptions.builds", "is_partial_stub_package": false, "is_stub": false, "names": {".class": "SymbolTable", "BuildException": {".class": "SymbolTableNode", "kind": "Gdef", "node": {".class": "TypeInfo", "_promote": null, "abstract_attributes": [], "bases": ["builtins.Exception"], "declared_metaclass": null, "defn": {".class": "ClassDef", "fullname": "pyexceptions.builds.BuildException", "name": "BuildException", "type_vars": []}, "flags": [], "fullname": "pyexceptions.builds.BuildException", "metaclass_type": null, "metadata": {}, "module_name": "pyexceptions.builds", "mro": ["pyexceptions.builds.BuildException", "builtins.Exception", "builtins.BaseException", "builtins.object"], "names": {".class": "SymbolTable", "__init__": {".class": "SymbolTableNode", "kind": "Mdef", "node": {".class": "FuncDef", "arg_kinds": [0, 0, 0], "arg_names": ["self", "msg", "build_output"], "flags": [], "fullname": "pyexceptions.builds.BuildException.__init__", "name": "__init__", "type": null}}, "build_output": {".class": "SymbolTableNode", "implicit": true, "kind": "Mdef", "node": {".class": "Var", "flags": [], "fullname": "pyexceptions.builds.BuildException.build_output", "name": "build_output", "type": {".class": "AnyType", "missing_import_name": null, "source_any": null, "type_of_any": 1}}}, "msg": {".class": "SymbolTableNode", "implicit": true, "kind": "Mdef", "node": {".class": "Var", "flags": [], "fullname": "pyexceptions.builds.BuildException.msg", "name": "msg", "type": {".class": "AnyType", "missing_import_name": null, "source_any": null, "type_of_any": 1}}}}, "tuple_type": null, "type_vars": [], "typeddict_type": null}}, "__doc__": {".class": "SymbolTableNode", "kind": "Gdef", "node": {".class": "Var", "flags": ["is_ready"], "fullname": "pyexceptions.builds.__doc__", "name": "__doc__", "type": "builtins.str"}}, "__file__": {".class": "SymbolTableNode", "kind": "Gdef", "node": {".class": "Var", "flags": ["is_ready"], "fullname": "pyexceptions.builds.__file__", "name": "__file__", "type": "builtins.str"}}, "__name__": {".class": "SymbolTableNode", "kind": "Gdef", "node": {".class": "Var", "flags": ["is_ready"], "fullname": "pyexceptions.builds.__name__", "name": "__name__", "type": "builtins.str"}}, "__package__": {".class": "SymbolTableNode", "kind": "Gdef", "node": {".class": "Var", "flags": ["is_ready"], "fullname": "pyexceptions.builds.__package__", "name": "__package__", "type": "builtins.str"}}}, "path": "pyexceptions/builds.py"}