{".class": "MypyFile", "_fullname": "models.initiate_database", "is_partial_stub_package": false, "is_stub": false, "names": {".class": "SymbolTable", "Base": {".class": "SymbolTableNode", "kind": "Gdef", "node": {".class": "TypeInfo", "_promote": null, "abstract_attributes": [], "bases": ["builtins.object"], "declared_metaclass": null, "defn": {".class": "ClassDef", "fullname": "models.initiate_database.Base", "name": "Base", "type_vars": []}, "flags": [], "fullname": "models.initiate_database.Base", "metaclass_type": null, "metadata": {"sqlalchemy": {"declarative_base": true}}, "module_name": "models.initiate_database", "mro": ["models.initiate_database.Base", "builtins.object"], "names": {".class": "SymbolTable", "metadata": {".class": "SymbolTableNode", "kind": "Mdef", "node": {".class": "Var", "flags": ["is_ready"], "fullname": "models.initiate_database.Base.metadata", "name": "metadata", "type": "sqlalchemy.sql.schema.MetaData"}}}, "tuple_type": null, "type_vars": [], "typeddict_type": null}}, "BigInteger": {".class": "SymbolTableNode", "cross_ref": "sqlalchemy.sql.sqltypes.BigInteger", "kind": "Gdef"}, "Binary": {".class": "SymbolTableNode", "cross_ref": "sqlalchemy.sql.sqltypes.Binary", "kind": "Gdef"}, "Boolean": {".class": "SymbolTableNode", "cross_ref": "sqlalchemy.sql.sqltypes.Boolean", "kind": "Gdef"}, "CHAR": {".class": "SymbolTableNode", "cross_ref": "sqlalchemy.sql.sqltypes.CHAR", "kind": "Gdef"}, "Column": {".class": "SymbolTableNode", "cross_ref": "sqlalchemy.sql.schema.Column", "kind": "Gdef"}, "DatabaseBindingSpec": {".class": "SymbolTableNode", "kind": "Gdef", "node": {".class": "TypeInfo", "_promote": null, "abstract_attributes": [], "bases": ["builtins.object"], "declared_metaclass": null, "defn": {".class": "ClassDef", "fullname": "models.initiate_database.DatabaseBindingSpec", "name": "DatabaseBindingSpec", "type_vars": []}, "flags": ["fallback_to_any"], "fullname": "models.initiate_database.DatabaseBindingSpec", "metaclass_type": null, "metadata": {}, "module_name": "models.initiate_database", "mro": ["models.initiate_database.DatabaseBindingSpec", "builtins.object"], "names": {".class": "SymbolTable", "configure": {".class": "SymbolTableNode", "kind": "Mdef", "node": {".class": "FuncDef", "arg_kinds": [0, 0], "arg_names": ["self", "bind"], "flags": [], "fullname": "models.initiate_database.DatabaseBindingSpec.configure", "name": "configure", "type": null}}, "provide_db_engine": {".class": "SymbolTableNode", "kind": "Mdef", "node": {".class": "Decorator", "func": {".class": "FuncDef", "arg_kinds": [0, 0], "arg_names": ["self", "app_config"], "flags": ["is_decorated"], "fullname": "models.initiate_database.DatabaseBindingSpec.provide_db_engine", "name": "provide_db_engine", "type": null}, "is_overload": false, "var": {".class": "Var", "flags": ["is_initialized_in_class", "is_ready"], "fullname": null, "name": "provide_db_engine", "type": {".class": "AnyType", "missing_import_name": "models.initiate_database.pinject", "source_any": {".class": "AnyType", "missing_import_name": "models.initiate_database.pinject", "source_any": null, "type_of_any": 3}, "type_of_any": 7}}}}, "provide_db_session_maker": {".class": "SymbolTableNode", "kind": "Mdef", "node": {".class": "Decorator", "func": {".class": "FuncDef", "arg_kinds": [0, 0], "arg_names": ["self", "db_engine"], "flags": ["is_decorated"], "fullname": "models.initiate_database.DatabaseBindingSpec.provide_db_session_maker", "name": "provide_db_session_maker", "type": null}, "is_overload": false, "var": {".class": "Var", "flags": ["is_initialized_in_class", "is_ready"], "fullname": null, "name": "provide_db_session_maker", "type": {".class": "AnyType", "missing_import_name": "models.initiate_database.pinject", "source_any": {".class": "AnyType", "missing_import_name": "models.initiate_database.pinject", "source_any": null, "type_of_any": 3}, "type_of_any": 7}}}}}, "tuple_type": null, "type_vars": [], "typeddict_type": null}}, "DateTime": {".class": "SymbolTableNode", "cross_ref": "sqlalchemy.sql.sqltypes.DateTime", "kind": "Gdef"}, "ForeignKey": {".class": "SymbolTableNode", "cross_ref": "sqlalchemy.sql.schema.ForeignKey", "kind": "Gdef"}, "Integer": {".class": "SymbolTableNode", "cross_ref": "sqlalchemy.sql.sqltypes.Integer", "kind": "Gdef"}, "JSON": {".class": "SymbolTableNode", "cross_ref": "sqlalchemy.sql.sqltypes.JSON", "kind": "Gdef"}, "String": {".class": "SymbolTableNode", "cross_ref": "sqlalchemy.sql.sqltypes.String", "kind": "Gdef"}, "Table": {".class": "SymbolTableNode", "cross_ref": "sqlalchemy.sql.schema.Table", "kind": "Gdef"}, "Text": {".class": "SymbolTableNode", "cross_ref": "sqlalchemy.sql.sqltypes.Text", "kind": "Gdef"}, "__doc__": {".class": "SymbolTableNode", "kind": "Gdef", "node": {".class": "Var", "flags": ["is_ready"], "fullname": "models.initiate_database.__doc__", "name": "__doc__", "type": "builtins.str"}}, "__file__": {".class": "SymbolTableNode", "kind": "Gdef", "node": {".class": "Var", "flags": ["is_ready"], "fullname": "models.initiate_database.__file__", "name": "__file__", "type": "builtins.str"}}, "__name__": {".class": "SymbolTableNode", "kind": "Gdef", "node": {".class": "Var", "flags": ["is_ready"], "fullname": "models.initiate_database.__name__", "name": "__name__", "type": "builtins.str"}}, "__package__": {".class": "SymbolTableNode", "kind": "Gdef", "node": {".class": "Var", "flags": ["is_ready"], "fullname": "models.initiate_database.__package__", "name": "__package__", "type": "builtins.str"}}, "contextmanager": {".class": "SymbolTableNode", "cross_ref": "contextlib.contextmanager", "kind": "Gdef"}, "create_engine": {".class": "SymbolTableNode", "cross_ref": "sqlalchemy.engine.create_engine", "kind": "Gdef"}, "create_scoped_db_session_maker": {".class": "SymbolTableNode", "kind": "Gdef", "node": {".class": "FuncDef", "arg_kinds": [0], "arg_names": ["engine"], "flags": [], "fullname": "models.initiate_database.create_scoped_db_session_maker", "name": "create_scoped_db_session_maker", "type": null}}, "declarative_base": {".class": "SymbolTableNode", "cross_ref": "sqlalchemy.ext.declarative.api.declarative_base", "kind": "Gdef"}, "engine_url_format": {".class": "SymbolTableNode", "kind": "Gdef", "node": {".class": "Var", "flags": ["is_ready"], "fullname": "models.initiate_database.engine_url_format", "name": "engine_url_format", "type": "builtins.str"}}, "event": {".class": "SymbolTableNode", "cross_ref": "sqlalchemy.event", "kind": "Gdef"}, "exc": {".class": "SymbolTableNode", "cross_ref": "sqlalchemy.exc", "kind": "Gdef"}, "func": {".class": "SymbolTableNode", "cross_ref": "sqlalchemy.sql.functions.func", "kind": "Gdef"}, "get_refinery_engine": {".class": "SymbolTableNode", "kind": "Gdef", "node": {".class": "FuncDef", "arg_kinds": [0], "arg_names": ["app_config"], "flags": [], "fullname": "models.initiate_database.get_refinery_engine", "name": "get_refinery_engine", "type": null}}, "os": {".class": "SymbolTableNode", "cross_ref": "os", "kind": "Gdef"}, "pinject": {".class": "SymbolTableNode", "kind": "Gdef", "node": {".class": "Var", "flags": ["is_suppressed_import", "is_ready"], "fullname": "models.initiate_database.pinject", "name": "pinject", "type": {".class": "AnyType", "missing_import_name": "models.initiate_database.pinject", "source_any": null, "type_of_any": 3}}}, "relationship": {".class": "SymbolTableNode", "cross_ref": "sqlalchemy.orm.relationship", "kind": "Gdef"}, "scoped_session": {".class": "SymbolTableNode", "cross_ref": "sqlalchemy.orm.scoping.scoped_session", "kind": "Gdef"}, "select": {".class": "SymbolTableNode", "cross_ref": "sqlalchemy.sql.expression.select", "kind": "Gdef"}, "sessionmaker": {".class": "SymbolTableNode", "cross_ref": "sqlalchemy.orm.session.sessionmaker", "kind": "Gdef"}, "sql_or": {".class": "SymbolTableNode", "cross_ref": "sqlalchemy.sql.expression.or_", "kind": "Gdef"}, "synonym": {".class": "SymbolTableNode", "cross_ref": "sqlalchemy.orm.synonym", "kind": "Gdef"}, "update": {".class": "SymbolTableNode", "cross_ref": "sqlalchemy.sql.expression.update", "kind": "Gdef"}, "yaml": {".class": "SymbolTableNode", "cross_ref": "yaml", "kind": "Gdef"}}, "path": "models/initiate_database.py"}