{".class": "MypyFile", "_fullname": "sqlalchemy.interfaces", "is_partial_stub_package": false, "is_stub": true, "names": {".class": "SymbolTable", "Any": {".class": "SymbolTableNode", "cross_ref": "typing.Any", "kind": "Gdef", "module_hidden": true, "module_public": false}, "ConnectionProxy": {".class": "SymbolTableNode", "kind": "Gdef", "node": {".class": "TypeInfo", "_promote": null, "abstract_attributes": [], "bases": ["builtins.object"], "declared_metaclass": null, "defn": {".class": "ClassDef", "fullname": "sqlalchemy.interfaces.ConnectionProxy", "name": "ConnectionProxy", "type_vars": []}, "flags": [], "fullname": "sqlalchemy.interfaces.ConnectionProxy", "metaclass_type": null, "metadata": {}, "module_name": "sqlalchemy.interfaces", "mro": ["sqlalchemy.interfaces.ConnectionProxy", "builtins.object"], "names": {".class": "SymbolTable", "begin": {".class": "SymbolTableNode", "kind": "Mdef", "node": {".class": "FuncDef", "arg_kinds": [0, 0, 0], "arg_names": ["self", "conn", "begin"], "flags": [], "fullname": "sqlalchemy.interfaces.ConnectionProxy.begin", "name": "begin", "type": null}}, "begin_twophase": {".class": "SymbolTableNode", "kind": "Mdef", "node": {".class": "FuncDef", "arg_kinds": [0, 0, 0, 0], "arg_names": ["self", "conn", "begin_twophase", "xid"], "flags": [], "fullname": "sqlalchemy.interfaces.ConnectionProxy.begin_twophase", "name": "begin_twophase", "type": null}}, "commit": {".class": "SymbolTableNode", "kind": "Mdef", "node": {".class": "FuncDef", "arg_kinds": [0, 0, 0], "arg_names": ["self", "conn", "commit"], "flags": [], "fullname": "sqlalchemy.interfaces.ConnectionProxy.commit", "name": "commit", "type": null}}, "commit_twophase": {".class": "SymbolTableNode", "kind": "Mdef", "node": {".class": "FuncDef", "arg_kinds": [0, 0, 0, 0, 0], "arg_names": ["self", "conn", "commit_twophase", "xid", "is_prepared"], "flags": [], "fullname": "sqlalchemy.interfaces.ConnectionProxy.commit_twophase", "name": "commit_twophase", "type": null}}, "cursor_execute": {".class": "SymbolTableNode", "kind": "Mdef", "node": {".class": "FuncDef", "arg_kinds": [0, 0, 0, 0, 0, 0, 0], "arg_names": ["self", "execute", "cursor", "statement", "parameters", "context", "executemany"], "flags": [], "fullname": "sqlalchemy.interfaces.ConnectionProxy.cursor_execute", "name": "cursor_execute", "type": null}}, "execute": {".class": "SymbolTableNode", "kind": "Mdef", "node": {".class": "FuncDef", "arg_kinds": [0, 0, 0, 0, 2, 4], "arg_names": ["self", "conn", "execute", "clauseelement", "multiparams", "params"], "flags": [], "fullname": "sqlalchemy.interfaces.ConnectionProxy.execute", "name": "execute", "type": null}}, "prepare_twophase": {".class": "SymbolTableNode", "kind": "Mdef", "node": {".class": "FuncDef", "arg_kinds": [0, 0, 0, 0], "arg_names": ["self", "conn", "prepare_twophase", "xid"], "flags": [], "fullname": "sqlalchemy.interfaces.ConnectionProxy.prepare_twophase", "name": "prepare_twophase", "type": null}}, "release_savepoint": {".class": "SymbolTableNode", "kind": "Mdef", "node": {".class": "FuncDef", "arg_kinds": [0, 0, 0, 0, 0], "arg_names": ["self", "conn", "release_savepoint", "name", "context"], "flags": [], "fullname": "sqlalchemy.interfaces.ConnectionProxy.release_savepoint", "name": "release_savepoint", "type": null}}, "rollback": {".class": "SymbolTableNode", "kind": "Mdef", "node": {".class": "FuncDef", "arg_kinds": [0, 0, 0], "arg_names": ["self", "conn", "rollback"], "flags": [], "fullname": "sqlalchemy.interfaces.ConnectionProxy.rollback", "name": "rollback", "type": null}}, "rollback_savepoint": {".class": "SymbolTableNode", "kind": "Mdef", "node": {".class": "FuncDef", "arg_kinds": [0, 0, 0, 0, 0], "arg_names": ["self", "conn", "rollback_savepoint", "name", "context"], "flags": [], "fullname": "sqlalchemy.interfaces.ConnectionProxy.rollback_savepoint", "name": "rollback_savepoint", "type": null}}, "rollback_twophase": {".class": "SymbolTableNode", "kind": "Mdef", "node": {".class": "FuncDef", "arg_kinds": [0, 0, 0, 0, 0], "arg_names": ["self", "conn", "rollback_twophase", "xid", "is_prepared"], "flags": [], "fullname": "sqlalchemy.interfaces.ConnectionProxy.rollback_twophase", "name": "rollback_twophase", "type": null}}, "savepoint": {".class": "SymbolTableNode", "kind": "Mdef", "node": {".class": "FuncDef", "arg_kinds": [0, 0, 0, 1], "arg_names": ["self", "conn", "savepoint", "name"], "flags": [], "fullname": "sqlalchemy.interfaces.ConnectionProxy.savepoint", "name": "savepoint", "type": {".class": "CallableType", "arg_kinds": [0, 0, 0, 1], "arg_names": ["self", "conn", "savepoint", "name"], "arg_types": ["sqlalchemy.interfaces.ConnectionProxy", {".class": "AnyType", "missing_import_name": null, "source_any": null, "type_of_any": 1}, {".class": "AnyType", "missing_import_name": null, "source_any": null, "type_of_any": 1}, {".class": "UnionType", "items": [{".class": "AnyType", "missing_import_name": null, "source_any": null, "type_of_any": 2}, {".class": "NoneType"}]}], "bound_args": [], "def_extras": {"first_arg": "self"}, "fallback": "builtins.function", "implicit": false, "is_ellipsis_args": false, "name": "savepoint of ConnectionProxy", "ret_type": {".class": "AnyType", "missing_import_name": null, "source_any": null, "type_of_any": 1}, "variables": []}}}}, "tuple_type": null, "type_vars": [], "typeddict_type": null}}, "Optional": {".class": "SymbolTableNode", "cross_ref": "typing.Optional", "kind": "Gdef", "module_hidden": true, "module_public": false}, "PoolListener": {".class": "SymbolTableNode", "kind": "Gdef", "node": {".class": "TypeInfo", "_promote": null, "abstract_attributes": [], "bases": ["builtins.object"], "declared_metaclass": null, "defn": {".class": "ClassDef", "fullname": "sqlalchemy.interfaces.PoolListener", "name": "PoolListener", "type_vars": []}, "flags": [], "fullname": "sqlalchemy.interfaces.PoolListener", "metaclass_type": null, "metadata": {}, "module_name": "sqlalchemy.interfaces", "mro": ["sqlalchemy.interfaces.PoolListener", "builtins.object"], "names": {".class": "SymbolTable", "checkin": {".class": "SymbolTableNode", "kind": "Mdef", "node": {".class": "FuncDef", "arg_kinds": [0, 0, 0], "arg_names": ["self", "dbapi_con", "con_record"], "flags": [], "fullname": "sqlalchemy.interfaces.PoolListener.checkin", "name": "checkin", "type": null}}, "checkout": {".class": "SymbolTableNode", "kind": "Mdef", "node": {".class": "FuncDef", "arg_kinds": [0, 0, 0, 0], "arg_names": ["self", "dbapi_con", "con_record", "con_proxy"], "flags": [], "fullname": "sqlalchemy.interfaces.PoolListener.checkout", "name": "checkout", "type": null}}, "connect": {".class": "SymbolTableNode", "kind": "Mdef", "node": {".class": "FuncDef", "arg_kinds": [0, 0, 0], "arg_names": ["self", "dbapi_con", "con_record"], "flags": [], "fullname": "sqlalchemy.interfaces.PoolListener.connect", "name": "connect", "type": null}}, "first_connect": {".class": "SymbolTableNode", "kind": "Mdef", "node": {".class": "FuncDef", "arg_kinds": [0, 0, 0], "arg_names": ["self", "dbapi_con", "con_record"], "flags": [], "fullname": "sqlalchemy.interfaces.PoolListener.first_connect", "name": "first_connect", "type": null}}}, "tuple_type": null, "type_vars": [], "typeddict_type": null}}, "__doc__": {".class": "SymbolTableNode", "kind": "Gdef", "node": {".class": "Var", "flags": ["is_ready"], "fullname": "sqlalchemy.interfaces.__doc__", "name": "__doc__", "type": "builtins.str"}}, "__file__": {".class": "SymbolTableNode", "kind": "Gdef", "node": {".class": "Var", "flags": ["is_ready"], "fullname": "sqlalchemy.interfaces.__file__", "name": "__file__", "type": "builtins.str"}}, "__name__": {".class": "SymbolTableNode", "kind": "Gdef", "node": {".class": "Var", "flags": ["is_ready"], "fullname": "sqlalchemy.interfaces.__name__", "name": "__name__", "type": "builtins.str"}}, "__package__": {".class": "SymbolTableNode", "kind": "Gdef", "node": {".class": "Var", "flags": ["is_ready"], "fullname": "sqlalchemy.interfaces.__package__", "name": "__package__", "type": "builtins.str"}}}, "path": "/home/free/code/refinery/env/lib/python3.8/site-packages/sqlalchemy-stubs/interfaces.pyi"}