{".class": "MypyFile", "_fullname": "sqlalchemy.orm", "is_partial_stub_package": false, "is_stub": true, "names": {".class": "SymbolTable", "AliasOption": {".class": "SymbolTableNode", "cross_ref": "sqlalchemy.orm.query.AliasOption", "kind": "Gdef"}, "Any": {".class": "SymbolTableNode", "cross_ref": "typing.Any", "kind": "Gdef", "module_hidden": true, "module_public": false}, "Bundle": {".class": "SymbolTableNode", "cross_ref": "sqlalchemy.orm.query.Bundle", "kind": "Gdef"}, "ColumnProperty": {".class": "SymbolTableNode", "cross_ref": "sqlalchemy.orm.properties.ColumnProperty", "kind": "Gdef"}, "ComparableProperty": {".class": "SymbolTableNode", "cross_ref": "sqlalchemy.orm.descriptor_props.ComparableProperty", "kind": "Gdef"}, "CompositeProperty": {".class": "SymbolTableNode", "cross_ref": "sqlalchemy.orm.descriptor_props.CompositeProperty", "kind": "Gdef"}, "EXT_CONTINUE": {".class": "SymbolTableNode", "cross_ref": "sqlalchemy.orm.base.EXT_CONTINUE", "kind": "Gdef"}, "EXT_STOP": {".class": "SymbolTableNode", "cross_ref": "sqlalchemy.orm.base.EXT_STOP", "kind": "Gdef"}, "Load": {".class": "SymbolTableNode", "cross_ref": "sqlalchemy.orm.strategy_options.Load", "kind": "Gdef"}, "Mapper": {".class": "SymbolTableNode", "cross_ref": "sqlalchemy.orm.mapper.Mapper", "kind": "Gdef"}, "Optional": {".class": "SymbolTableNode", "cross_ref": "typing.Optional", "kind": "Gdef", "module_hidden": true, "module_public": false}, "PropComparator": {".class": "SymbolTableNode", "cross_ref": "sqlalchemy.orm.interfaces.PropComparator", "kind": "Gdef"}, "Query": {".class": "SymbolTableNode", "cross_ref": "sqlalchemy.orm.query.Query", "kind": "Gdef"}, "RelationshipProperty": {".class": "SymbolTableNode", "cross_ref": "sqlalchemy.orm.relationships.RelationshipProperty", "kind": "Gdef"}, "Session": {".class": "SymbolTableNode", "cross_ref": "sqlalchemy.orm.session.Session", "kind": "Gdef"}, "SynonymProperty": {".class": "SymbolTableNode", "cross_ref": "sqlalchemy.orm.descriptor_props.SynonymProperty", "kind": "Gdef"}, "__doc__": {".class": "SymbolTableNode", "kind": "Gdef", "node": {".class": "Var", "flags": ["is_ready"], "fullname": "sqlalchemy.orm.__doc__", "name": "__doc__", "type": "builtins.str"}}, "__file__": {".class": "SymbolTableNode", "kind": "Gdef", "node": {".class": "Var", "flags": ["is_ready"], "fullname": "sqlalchemy.orm.__file__", "name": "__file__", "type": "builtins.str"}}, "__name__": {".class": "SymbolTableNode", "kind": "Gdef", "node": {".class": "Var", "flags": ["is_ready"], "fullname": "sqlalchemy.orm.__name__", "name": "__name__", "type": "builtins.str"}}, "__package__": {".class": "SymbolTableNode", "kind": "Gdef", "node": {".class": "Var", "flags": ["is_ready"], "fullname": "sqlalchemy.orm.__package__", "name": "__package__", "type": "builtins.str"}}, "aliased": {".class": "SymbolTableNode", "cross_ref": "sqlalchemy.orm.util.aliased", "kind": "Gdef"}, "backref": {".class": "SymbolTableNode", "kind": "Gdef", "node": {".class": "FuncDef", "arg_kinds": [0, 4], "arg_names": ["name", "kwargs"], "flags": [], "fullname": "sqlalchemy.orm.backref", "name": "backref", "type": null}}, "class_mapper": {".class": "SymbolTableNode", "cross_ref": "sqlalchemy.orm.base.class_mapper", "kind": "Gdef"}, "clear_mappers": {".class": "SymbolTableNode", "kind": "Gdef", "node": {".class": "FuncDef", "arg_kinds": [], "arg_names": [], "flags": [], "fullname": "sqlalchemy.orm.clear_mappers", "name": "clear_mappers", "type": null}}, "column_property": {".class": "SymbolTableNode", "kind": "Gdef", "node": {".class": "TypeAlias", "alias_tvars": [], "column": 0, "fullname": "sqlalchemy.orm.column_property", "line": 51, "no_args": true, "normalized": false, "target": "sqlalchemy.orm.properties.ColumnProperty"}}, "comparable_property": {".class": "SymbolTableNode", "kind": "Gdef", "node": {".class": "TypeAlias", "alias_tvars": [], "column": 0, "fullname": "sqlalchemy.orm.comparable_property", "line": 61, "no_args": true, "normalized": false, "target": "sqlalchemy.orm.descriptor_props.ComparableProperty"}}, "compile_mappers": {".class": "SymbolTableNode", "kind": "Gdef", "node": {".class": "FuncDef", "arg_kinds": [], "arg_names": [], "flags": [], "fullname": "sqlalchemy.orm.compile_mappers", "name": "compile_mappers", "type": null}}, "composite": {".class": "SymbolTableNode", "kind": "Gdef", "node": {".class": "TypeAlias", "alias_tvars": [], "column": 0, "fullname": "sqlalchemy.orm.composite", "line": 52, "no_args": true, "normalized": false, "target": "sqlalchemy.orm.descriptor_props.CompositeProperty"}}, "configure_mappers": {".class": "SymbolTableNode", "cross_ref": "sqlalchemy.orm.mapper.configure_mappers", "kind": "Gdef"}, "contains_alias": {".class": "SymbolTableNode", "kind": "Gdef", "node": {".class": "TypeAlias", "alias_tvars": [], "column": 0, "fullname": "sqlalchemy.orm.contains_alias", "line": 90, "no_args": true, "normalized": false, "target": "sqlalchemy.orm.query.AliasOption"}}, "contains_eager": {".class": "SymbolTableNode", "kind": "Gdef", "node": {".class": "Var", "flags": ["is_ready"], "fullname": "sqlalchemy.orm.contains_eager", "name": "contains_eager", "type": {".class": "AnyType", "missing_import_name": null, "source_any": null, "type_of_any": 2}}}, "create_session": {".class": "SymbolTableNode", "kind": "Gdef", "node": {".class": "FuncDef", "arg_kinds": [1, 4], "arg_names": ["bind", "kwargs"], "flags": [], "fullname": "sqlalchemy.orm.create_session", "name": "create_session", "type": {".class": "CallableType", "arg_kinds": [1, 4], "arg_names": ["bind", "kwargs"], "arg_types": [{".class": "UnionType", "items": [{".class": "AnyType", "missing_import_name": null, "source_any": null, "type_of_any": 2}, {".class": "NoneType"}]}, {".class": "AnyType", "missing_import_name": null, "source_any": null, "type_of_any": 1}], "bound_args": [], "def_extras": {"first_arg": null}, "fallback": "builtins.function", "implicit": false, "is_ellipsis_args": false, "name": "create_session", "ret_type": {".class": "AnyType", "missing_import_name": null, "source_any": null, "type_of_any": 1}, "variables": []}}}, "defaultload": {".class": "SymbolTableNode", "kind": "Gdef", "node": {".class": "Var", "flags": ["is_ready"], "fullname": "sqlalchemy.orm.defaultload", "name": "defaultload", "type": {".class": "AnyType", "missing_import_name": null, "source_any": null, "type_of_any": 2}}}, "defer": {".class": "SymbolTableNode", "kind": "Gdef", "node": {".class": "Var", "flags": ["is_ready"], "fullname": "sqlalchemy.orm.defer", "name": "defer", "type": {".class": "AnyType", "missing_import_name": null, "source_any": null, "type_of_any": 2}}}, "deferred": {".class": "SymbolTableNode", "kind": "Gdef", "node": {".class": "FuncDef", "arg_kinds": [2, 4], "arg_names": ["columns", "kw"], "flags": [], "fullname": "sqlalchemy.orm.deferred", "name": "deferred", "type": null}}, "dynamic_loader": {".class": "SymbolTableNode", "kind": "Gdef", "node": {".class": "FuncDef", "arg_kinds": [0, 4], "arg_names": ["argument", "kw"], "flags": [], "fullname": "sqlalchemy.orm.dynamic_loader", "name": "dynamic_loader", "type": null}}, "eagerload": {".class": "SymbolTableNode", "kind": "Gdef", "node": {".class": "FuncDef", "arg_kinds": [2, 4], "arg_names": ["args", "kwargs"], "flags": [], "fullname": "sqlalchemy.orm.eagerload", "name": "eagerload", "type": null}}, "eagerload_all": {".class": "SymbolTableNode", "kind": "Gdef", "node": {".class": "FuncDef", "arg_kinds": [2, 4], "arg_names": ["args", "kwargs"], "flags": [], "fullname": "sqlalchemy.orm.eagerload_all", "name": "eagerload_all", "type": null}}, "foreign": {".class": "SymbolTableNode", "cross_ref": "sqlalchemy.orm.relationships.foreign", "kind": "Gdef"}, "immediateload": {".class": "SymbolTableNode", "kind": "Gdef", "node": {".class": "Var", "flags": ["is_ready"], "fullname": "sqlalchemy.orm.immediateload", "name": "immediateload", "type": {".class": "AnyType", "missing_import_name": null, "source_any": null, "type_of_any": 2}}}, "join": {".class": "SymbolTableNode", "cross_ref": "sqlalchemy.orm.util.join", "kind": "Gdef"}, "joinedload": {".class": "SymbolTableNode", "kind": "Gdef", "node": {".class": "Var", "flags": ["is_ready"], "fullname": "sqlalchemy.orm.joinedload", "name": "joinedload", "type": {".class": "AnyType", "missing_import_name": null, "source_any": null, "type_of_any": 2}}}, "joinedload_all": {".class": "SymbolTableNode", "kind": "Gdef", "node": {".class": "Var", "flags": ["is_ready"], "fullname": "sqlalchemy.orm.joinedload_all", "name": "joinedload_all", "type": {".class": "AnyType", "missing_import_name": null, "source_any": null, "type_of_any": 2}}}, "lazyload": {".class": "SymbolTableNode", "kind": "Gdef", "node": {".class": "Var", "flags": ["is_ready"], "fullname": "sqlalchemy.orm.lazyload", "name": "lazyload", "type": {".class": "AnyType", "missing_import_name": null, "source_any": null, "type_of_any": 2}}}, "lazyload_all": {".class": "SymbolTableNode", "kind": "Gdef", "node": {".class": "Var", "flags": ["is_ready"], "fullname": "sqlalchemy.orm.lazyload_all", "name": "lazyload_all", "type": {".class": "AnyType", "missing_import_name": null, "source_any": null, "type_of_any": 2}}}, "load_only": {".class": "SymbolTableNode", "kind": "Gdef", "node": {".class": "Var", "flags": ["is_ready"], "fullname": "sqlalchemy.orm.load_only", "name": "load_only", "type": {".class": "AnyType", "missing_import_name": null, "source_any": null, "type_of_any": 2}}}, "make_transient": {".class": "SymbolTableNode", "cross_ref": "sqlalchemy.orm.session.make_transient", "kind": "Gdef"}, "make_transient_to_detached": {".class": "SymbolTableNode", "cross_ref": "sqlalchemy.orm.session.make_transient_to_detached", "kind": "Gdef"}, "mapper": {".class": "SymbolTableNode", "kind": "Gdef", "node": {".class": "TypeAlias", "alias_tvars": [], "column": 0, "fullname": "sqlalchemy.orm.mapper", "line": 59, "no_args": true, "normalized": false, "target": "sqlalchemy.orm.mapper.Mapper"}}, "mapperlib": {".class": "SymbolTableNode", "cross_ref": "sqlalchemy.orm.mapper", "kind": "Gdef"}, "noload": {".class": "SymbolTableNode", "kind": "Gdef", "node": {".class": "Var", "flags": ["is_ready"], "fullname": "sqlalchemy.orm.noload", "name": "noload", "type": {".class": "AnyType", "missing_import_name": null, "source_any": null, "type_of_any": 2}}}, "object_mapper": {".class": "SymbolTableNode", "cross_ref": "sqlalchemy.orm.base.object_mapper", "kind": "Gdef"}, "object_session": {".class": "SymbolTableNode", "cross_ref": "sqlalchemy.orm.session.object_session", "kind": "Gdef"}, "outerjoin": {".class": "SymbolTableNode", "cross_ref": "sqlalchemy.orm.util.outerjoin", "kind": "Gdef"}, "polymorphic_union": {".class": "SymbolTableNode", "cross_ref": "sqlalchemy.orm.util.polymorphic_union", "kind": "Gdef"}, "query_expression": {".class": "SymbolTableNode", "kind": "Gdef", "node": {".class": "FuncDef", "arg_kinds": [], "arg_names": [], "flags": [], "fullname": "sqlalchemy.orm.query_expression", "name": "query_expression", "type": {".class": "CallableType", "arg_kinds": [], "arg_names": [], "arg_types": [], "bound_args": [], "def_extras": {"first_arg": null}, "fallback": "builtins.function", "implicit": false, "is_ellipsis_args": false, "name": "query_expression", "ret_type": "sqlalchemy.orm.properties.ColumnProperty", "variables": []}}}, "raiseload": {".class": "SymbolTableNode", "kind": "Gdef", "node": {".class": "Var", "flags": ["is_ready"], "fullname": "sqlalchemy.orm.raiseload", "name": "raiseload", "type": {".class": "AnyType", "missing_import_name": null, "source_any": null, "type_of_any": 2}}}, "reconstructor": {".class": "SymbolTableNode", "cross_ref": "sqlalchemy.orm.mapper.reconstructor", "kind": "Gdef"}, "relation": {".class": "SymbolTableNode", "kind": "Gdef", "node": {".class": "FuncDef", "arg_kinds": [2, 4], "arg_names": ["arg", "kw"], "flags": [], "fullname": "sqlalchemy.orm.relation", "name": "relation", "type": null}}, "relationship": {".class": "SymbolTableNode", "kind": "Gdef", "node": {".class": "TypeAlias", "alias_tvars": [], "column": 0, "fullname": "sqlalchemy.orm.relationship", "line": 46, "no_args": true, "normalized": false, "target": {".class": "Instance", "args": [{".class": "AnyType", "missing_import_name": null, "source_any": null, "type_of_any": 4}], "type_ref": "sqlalchemy.orm.relationships.RelationshipProperty"}}}, "remote": {".class": "SymbolTableNode", "cross_ref": "sqlalchemy.orm.relationships.remote", "kind": "Gdef"}, "scoped_session": {".class": "SymbolTableNode", "cross_ref": "sqlalchemy.orm.scoping.scoped_session", "kind": "Gdef"}, "selectin_polymorphic": {".class": "SymbolTableNode", "kind": "Gdef", "node": {".class": "Var", "flags": ["is_ready"], "fullname": "sqlalchemy.orm.selectin_polymorphic", "name": "selectin_polymorphic", "type": {".class": "AnyType", "missing_import_name": null, "source_any": null, "type_of_any": 2}}}, "selectinload": {".class": "SymbolTableNode", "kind": "Gdef", "node": {".class": "Var", "flags": ["is_ready"], "fullname": "sqlalchemy.orm.selectinload", "name": "selectinload", "type": {".class": "AnyType", "missing_import_name": null, "source_any": null, "type_of_any": 2}}}, "selectinload_all": {".class": "SymbolTableNode", "kind": "Gdef", "node": {".class": "Var", "flags": ["is_ready"], "fullname": "sqlalchemy.orm.selectinload_all", "name": "selectinload_all", "type": {".class": "AnyType", "missing_import_name": null, "source_any": null, "type_of_any": 2}}}, "sessionmaker": {".class": "SymbolTableNode", "cross_ref": "sqlalchemy.orm.session.sessionmaker", "kind": "Gdef"}, "subqueryload": {".class": "SymbolTableNode", "kind": "Gdef", "node": {".class": "Var", "flags": ["is_ready"], "fullname": "sqlalchemy.orm.subqueryload", "name": "subqueryload", "type": {".class": "AnyType", "missing_import_name": null, "source_any": null, "type_of_any": 2}}}, "subqueryload_all": {".class": "SymbolTableNode", "kind": "Gdef", "node": {".class": "Var", "flags": ["is_ready"], "fullname": "sqlalchemy.orm.subqueryload_all", "name": "subqueryload_all", "type": {".class": "AnyType", "missing_import_name": null, "source_any": null, "type_of_any": 2}}}, "synonym": {".class": "SymbolTableNode", "kind": "Gdef", "node": {".class": "TypeAlias", "alias_tvars": [], "column": 0, "fullname": "sqlalchemy.orm.synonym", "line": 60, "no_args": true, "normalized": false, "target": "sqlalchemy.orm.descriptor_props.SynonymProperty"}}, "undefer": {".class": "SymbolTableNode", "kind": "Gdef", "node": {".class": "Var", "flags": ["is_ready"], "fullname": "sqlalchemy.orm.undefer", "name": "undefer", "type": {".class": "AnyType", "missing_import_name": null, "source_any": null, "type_of_any": 2}}}, "undefer_group": {".class": "SymbolTableNode", "kind": "Gdef", "node": {".class": "Var", "flags": ["is_ready"], "fullname": "sqlalchemy.orm.undefer_group", "name": "undefer_group", "type": {".class": "AnyType", "missing_import_name": null, "source_any": null, "type_of_any": 2}}}, "validates": {".class": "SymbolTableNode", "cross_ref": "sqlalchemy.orm.mapper.validates", "kind": "Gdef"}, "was_deleted": {".class": "SymbolTableNode", "cross_ref": "sqlalchemy.orm.util.was_deleted", "kind": "Gdef"}, "with_expression": {".class": "SymbolTableNode", "kind": "Gdef", "node": {".class": "Var", "flags": ["is_ready"], "fullname": "sqlalchemy.orm.with_expression", "name": "with_expression", "type": {".class": "AnyType", "missing_import_name": null, "source_any": null, "type_of_any": 2}}}, "with_parent": {".class": "SymbolTableNode", "cross_ref": "sqlalchemy.orm.util.with_parent", "kind": "Gdef"}, "with_polymorphic": {".class": "SymbolTableNode", "cross_ref": "sqlalchemy.orm.util.with_polymorphic", "kind": "Gdef"}}, "path": "/home/free/code/refinery/env/lib/python3.8/site-packages/sqlalchemy-stubs/orm/__init__.pyi"}